{"arrobjsum.md":"0cd3bb3f","assign.md":"86506e64","assignmin.md":"5eca27fd","bytesize.md":"27c8f0b3","chunk.md":"b276dec4","compact.md":"7f6acd69","createdata.md":"75271ada","day.md":"10dc5286","days.md":"5d1f49a0","debounce.md":"3852b96e","deepclone.md":"4289babe","deepcopy.md":"46c4a9e7","detectdevicetype.md":"aa5e8bc6","downloadfile.md":"3d934fac","extendhex.md":"f08d1947","frompairs.md":"1d16b03c","gbktoutf8.md":"f61bfe3f","getdatasection.md":"b8801967","getdatatype.md":"4f418f62","getformatdatetime.md":"b59435fb","getmonthnum.md":"cc1f8933","getrandom.md":"0c47765c","gettimestamp.md":"e716b8fd","getuuid.md":"3a0bf0a4","geturlparam.md":"839ea0c7","geturlquery.md":"00fb47d4","hextorgb.md":"42098170","howlongago.md":"69988c8b","index.md":"fb1f4b84","isandroid.md":"399f0e8b","isarrobj.md":"2c9e61ab","isarray.md":"d042cb00","isboolean.md":"1b69f4bc","isdate.md":"9cea5d60","isdesktop.md":"77fbb788","isdom.md":"fdd5470b","isemptyobject.md":"ea2b3620","isfunction.md":"fc3f4554","ishex.md":"ffde5671","isios.md":"c1ce8342","isincludechinese.md":"002a6637","isint.md":"3a43f9b4","islocation.md":"d737d5d8","ismap.md":"d9acbf81","ismobile.md":"e177cbde","isnullorundefined.md":"bb042aa5","isnumber.md":"fb91bf30","isobject.md":"abdc96dd","isphone.md":"26571a7f","ispromise.md":"758f233a","isqq.md":"844faf4f","isrgba.md":"8d118d58","isset.md":"8cbdf069","isstring.md":"4963a56d","issymbol.md":"50c9ef4e","isurl.md":"9d07b488","isweixin.md":"b41d69d1","isweixinmini.md":"e8c616a6","iswin.md":"f2d7d1ab","mask.md":"b65dad06","omit.md":"cd1dcd95","padint.md":"d4a5ae0b","phoneencrypt.md":"0b9a23ff","qsparse.md":"3a8722df","qsstringify.md":"021ec743","randomhex.md":"ad8b0e1a","randomrgba.md":"eafa63d1","removehtml.md":"a453a4ad","returnstr.md":"f8a9a164","rgbtohex.md":"fb1db01a","scrollto.md":"364b1239","shrinkhex.md":"a471bd65","start.md":"b1fbd53e","throttle.md":"4fef8da4","tofixed.md":"1e36a91f","tonumber.md":"0f26df15","unique.md":"b3f9f7b2","upperfirst.md":"f8524ea4"}
