{"chunk.md":"7c4fc842","compact.md":"23ded2b1","createdata.md":"8e74894e","debounce.md":"65c9c9e9","deepclone.md":"8c13a876","deepcopy.md":"88de6f2e","detectdevicetype.md":"4576729e","downloadfile.md":"0262e49b","frompairs.md":"394ae213","gbktoutf8.md":"c3d9a20f","getdatatype.md":"a67cbfa9","getformatdatetime.md":"90c483c0","getmonthnum.md":"dd9a3418","getrandom.md":"d2633649","gettimestamp.md":"a7213862","getuuid.md":"39efbf98","geturlparam.md":"bcaae9f5","howlongago.md":"fb42f8e1","index.md":"dd0d38cd","isandroid.md":"a392838c","isarray.md":"6661e4c4","isboolean.md":"1ff83ad2","isdate.md":"035dc4a7","isdesktop.md":"6521c81c","isdom.md":"fedca655","isemptyobject.md":"828fc3c1","isfunction.md":"3deba612","isios.md":"977b4f97","isincludechinese.md":"93108a30","islocation.md":"5a6d3d32","ismap.md":"6e271aa5","ismobile.md":"3c2fbef9","isnumber.md":"84a3247d","isobject.md":"567b5d4a","isphone.md":"9f01c372","ispromise.md":"cab27fc3","isset.md":"9f36f635","isstring.md":"0e199025","issymbol.md":"d7be09d9","padint.md":"77c2c7e5","phoneencrypt.md":"0c0a4d3c","returnstr.md":"839fb594","scrollto.md":"4e697dd4","start.md":"bf280e6f","throttle.md":"b9ee77d2","tofixed.md":"fabc0b00","tonumber.md":"175b6a7b","unique.md":"a481d170","upperfirst.md":"d0f894be"}
